odoo8_addon_geoengine_project-8.0.0.1.0.99.dev6-py2.7-nspkg.pth
odoo8_addon_geoengine_project-8.0.0.1.0.99.dev6.dist-info/DESCRIPTION.rst
odoo8_addon_geoengine_project-8.0.0.1.0.99.dev6.dist-info/METADATA
odoo8_addon_geoengine_project-8.0.0.1.0.99.dev6.dist-info/RECORD
odoo8_addon_geoengine_project-8.0.0.1.0.99.dev6.dist-info/WHEEL
odoo8_addon_geoengine_project-8.0.0.1.0.99.dev6.dist-info/metadata.json
odoo8_addon_geoengine_project-8.0.0.1.0.99.dev6.dist-info/namespace_packages.txt
odoo8_addon_geoengine_project-8.0.0.1.0.99.dev6.dist-info/top_level.txt
odoo_addons/geoengine_project/README.rst
odoo_addons/geoengine_project/__init__.py
odoo_addons/geoengine_project/__openerp__.py
odoo_addons/geoengine_project/i18n/de.po
odoo_addons/geoengine_project/i18n/es_MX.po
odoo_addons/geoengine_project/i18n/fi.po
odoo_addons/geoengine_project/i18n/fr.po
odoo_addons/geoengine_project/i18n/sl.po
odoo_addons/geoengine_project/i18n/zh_CN.po
odoo_addons/geoengine_project/models/__init__.py
odoo_addons/geoengine_project/models/project_project.py
odoo_addons/geoengine_project/static/description/icon.png
odoo_addons/geoengine_project/tests/__init__.py
odoo_addons/geoengine_project/tests/test_geoengine_project.py
odoo_addons/geoengine_project/views/geo_project_view.xml
